Workbook

Sheet 📊 KPI Dashboard
A1: TOMORROWNEEDS - SUBSCRIPTION BUSINESS EXECUTIVE DASHBOARD
A3: Real-time Metrics: Monthly Recurring Revenue (MRR), Active Subscribers, Delivery Fulfillment & Fee Collections
B5: ACTIVE SUBSCRIBERS | C5: MONTHLY REC. REVENUE (MRR) | D5: FEES COLLECTED (MTD) | E5: PENDING DUES | F5: DAILY DELIVERIES TODAY
B6: ='👥 Subscriptions Master'!L2 | C6: =SUM('👥 Subscriptions Master'!I3:I50) | D6: =SUM('💰 Fee Collection'!G3:G50) | E6: =SUM('💰 Fee Collection'!K3:K50) | F6: =COUNTIF('🚚 Daily Delivery Log'!G3:G100, "Delivered")
B7: Total paid active customers | C7: Expected monthly revenue | D7: Realized revenue collected | E7: Outstanding payment balance | F7: Successful daily drop-offs
B9: HOW TO TRACK YOUR BUSINESS (DAILY, WEEKLY, MONTHLY CADENCE)
B10: Cadence | C10: Responsible | D10: Key Activities to Review | E10: Target KPI / Health Indicator
B11: DAILY (Evening 7:00 PM) | C11: Store Operations | D11: Review pause/resume requests for tomorrow; check raw milk/batter/veggie procurement count. | E11: 0 Missed deliveries, 100% order prep by 6:00 AM
B12: DAILY (Morning 8:30 AM) | C12: Delivery Fleet | D12: Verify morning doorstep drops (Log sheet); flag unreachable customers or wrong gate drops. | E12: Fulfillment Rate > 99.5% by 7:00 AM
B13: DAILY (Midday 12:00 PM) | C13: Accounts / Admin | D13: Check wallet balances < ₹200; auto-remind customers via WhatsApp / App push to top up. | E13: Wallet health > 80% positive balance
B14: WEEKLY (Every Monday) | C14: Growth & Marketing | D14: Analyze new subscription additions vs cancellations (churn); review trial-to-paid conversion. | E14: Weekly Net Growth Rate > 5%
B15: WEEKLY (Every Friday) | C15: Procurement / Vendors | D15: Reconcile vendor batch rates, wastage % (greens/fruits), and packaging supply inventory. | E15: Wastage Loss < 3.5% of total procurement
B16: MONTHLY (1st of Month) | C16: Business Owner | D16: Audit MRR, total fees collected, subscription renewals, average customer lifetime value (LTV). | E16: Collection Efficiency > 98%, Churn < 4%

Sheet 👥 Subscriptions Master
A1: TOMORROWNEEDS - ACTIVE & RECURRING SUBSCRIPTIONS MASTER DIRECTORY
A2: Cust ID | B2: Customer Name | C2: Phone / WhatsApp | D2: Delivery Zone / Pincode | E2: Door / Flat / Apartment | F2: Subscribed Plan / Items | G2: Frequency | H2: Daily Qty | I2: Monthly Plan Fee (₹) | J2: Start Date | K2: Status | L2: Wallet Balance (₹) | M2: Next Billing Date | N2: Auto-Renew
A3: TN-SUB-101 | B3: Ramesh Kumar | C3: 9840123456 | D3: Chennai - 600095 | E3: Flat 402, Green Acres Apt | F3: Farm Fresh Buffalo Milk | G3: Daily | H3: 1 Litre | I3: 2100 | J3: 2026-09-01 | K3: Active | L3: 850 | M3: 2026-11-01 | N3: Yes (Wallet)
A4: TN-SUB-102 | B4: Priya Sundaram | C4: 9840234567 | D4: Chennai - 600095 | E4: Plot 12, Anna Nagar West | F4: Stoneground Idli/Dosa Batter | G4: Alternate Days | H4: 1 Kg | I4: 750 | J4: 2026-09-15 | K4: Active | L4: 420 | M4: 2026-10-15 | N4: Yes (Wallet)
A5: TN-SUB-103 | B5: Anand Venkatesh | C5: 9840345678 | D5: Chennai - 600028 | E5: Villa 9, Palm Meadows | F5: Organic Vegetables Basket (5kg) | G5: Weekly (Sat) | H5: 1 Basket | I5: 1400 | J5: 2026-08-01 | K5: Active | L5: 1200 | M5: 2026-11-01 | N5: Manual UPI
A6: TN-SUB-104 | B6: Deepa Mohan | C6: 9840456789 | D6: Chennai - 600095 | E6: Door 18, 3rd Cross Street | F6: Fresh Country Cow Milk | G6: Daily | H6: 500 ml | I6: 1200 | J6: 2026-09-20 | K6: Active | L6: 150 | M6: 2026-10-20 | N6: Yes (Wallet)
A7: TN-SUB-105 | B7: Karthik Subramanian | C7: 9840567890 | D7: Chennai - 600041 | E7: B-301, Skyline Towers | F7: Cold-Pressed Sesame & Groundnut Oil | G7: Monthly | H7: 2 Litres | I7: 900 | J7: 2026-09-01 | K7: Active | L7: 900 | M7: 2026-11-01 | N7: Yes (Wallet)
A8: TN-SUB-106 | B8: Sneha Balaji | C8: 9840678901 | D8: Chennai - 600095 | E8: Flat 104, Oasis Heights | F8: Fresh Greens & Spinach Combo | G8: Mon / Wed / Fri | H8: 2 Bunches | I8: 480 | J8: 2026-10-01 | K8: Paused | L8: 300 | M8: 2026-11-01 | N8: Manual UPI
A9: TN-SUB-107 | B9: Manoj Prabhakar | C9: 9840789012 | D9: Chennai - 600028 | E9: No 54, Gandhi Road | F9: Farm Fresh Cow Milk + Batter | G9: Daily | H9: 1L + 1Kg | I9: 2850 | J9: 2026-07-01 | K9: Active | L9: 2100 | M9: 2026-11-01 | N9: Yes (Wallet)

Sheet 🚚 Daily Delivery Log
A1: TOMORROWNEEDS - MORNING 7:00 AM FULFILLMENT & DISPATCH LOG
A2: Date | B2: Slot Time | C2: Cust ID | D2: Customer Name | E2: Delivery Address | F2: Subscribed Items to Pack | G2: Fulfillment Status | H2: Delivery Executive | I2: Delivered At | J2: Customer Notes / Gate Code
A3: 2026-10-04 | B3: 06:00 - 07:00 AM | C3: TN-SUB-101 | D3: Ramesh Kumar | E3: Flat 402, Green Acres Apt | F3: 1L Buffalo Milk (Chilled Pouch) | G3: Delivered | H3: Murugan (Rider 1) | I3: 06:22 AM | J3: Leave inside door bag
A4: 2026-10-04 | B4: 06:00 - 07:00 AM | C4: TN-SUB-102 | D4: Priya Sundaram | E4: Plot 12, Anna Nagar West | F4: 1Kg Idli/Dosa Batter | G4: Delivered | H4: Murugan (Rider 1) | I4: 06:35 AM | J4: Ring bell once
A5: 2026-10-04 | B5: 06:00 - 07:00 AM | C5: TN-SUB-104 | D5: Deepa Mohan | E5: Door 18, 3rd Cross Street | F5: 500ml Country Cow Milk | G5: Delivered | H5: Saravanan (Rider 2) | I5: 06:15 AM | J5: Keep in milk box
A6: 2026-10-04 | B6: 06:00 - 07:00 AM | C6: TN-SUB-107 | D6: Manoj Prabhakar | E6: No 54, Gandhi Road | F6: 1L Cow Milk + 1Kg Batter | G6: Delivered | H6: Saravanan (Rider 2) | I6: 06:48 AM | J6: Door hook drop
A7: 2026-10-05 | B7: 06:00 - 07:00 AM | C7: TN-SUB-101 | D7: Ramesh Kumar | E7: Flat 402, Green Acres Apt | F7: 1L Buffalo Milk | G7: Scheduled | H7: Murugan (Rider 1) | I7: -- | J7: Door bag
A8: 2026-10-05 | B8: 06:00 - 07:00 AM | C8: TN-SUB-104 | D8: Deepa Mohan | E8: Door 18, 3rd Cross Street | F8: 500ml Country Cow Milk | G8: Scheduled | H8: Saravanan (Rider 2) | I8: -- | J8: Milk box
A9: 2026-10-05 | B9: 06:00 - 07:00 AM | C9: TN-SUB-107 | D9: Manoj Prabhakar | E9: No 54, Gandhi Road | F9: 1L Cow Milk + 1Kg Batter | G9: Scheduled | H9: Saravanan (Rider 2) | I9: -- | J9: Door hook

Sheet 💰 Fee Collection
A1: TOMORROWNEEDS - SUBSCRIPTION FEES & PAYMENT RECONCILIATION
A2: Invoice # | B2: Cust ID | C2: Customer Name | D2: Billing Cycle | E2: Plan Fee (₹) | F2: Extra Orders (₹) | G2: Total Billed (₹) | H2: Paid via Wallet (₹) | I2: Paid via UPI / Card (₹) | J2: Cash / Direct (₹) | K2: Balance Due (₹) | L2: Payment Status | M2: Txn Reference / Notes | N2: Payment Date
A3: INV-2026-1001 | B3: TN-SUB-101 | C3: Ramesh Kumar | D3: Oct 2026 (Monthly) | E3: 2100 | F3: 180 | G3: =E3+F3 | H3: 2280 | I3: 0 | J3: 0 | K3: =G3-(H3+I3+J3) | L3: Paid in Full | M3: Auto-deducted from Wallet | N3: 2026-10-01
A4: INV-2026-1002 | B4: TN-SUB-102 | C4: Priya Sundaram | D4: Oct 2026 (Monthly) | E4: 750 | F4: 0 | G4: =E4+F4 | H4: 750 | I4: 0 | J4: 0 | K4: =G4-(H4+I4+J4) | L4: Paid in Full | M4: Wallet auto-debit | N4: 2026-10-01
A5: INV-2026-1003 | B5: TN-SUB-103 | C5: Anand Venkatesh | D5: Oct 2026 (Monthly) | E5: 1400 | F5: 320 | G5: =E5+F5 | H5: 0 | I5: 1720 | J5: 0 | K5: =G5-(H5+I5+J5) | L5: Paid in Full | M5: Razorpay UPI (rzp_live_xxx) | N5: 2026-10-02
A6: INV-2026-1004 | B6: TN-SUB-104 | C6: Deepa Mohan | D6: Oct 2026 (Monthly) | E6: 1200 | F6: 0 | G6: =E6+F6 | H6: 150 | I6: 0 | J6: 0 | K6: =G6-(H6+I6+J6) | L6: Pending Dues | M6: Insufficient wallet; reminder sent | N6: Pending
A7: INV-2026-1005 | B7: TN-SUB-105 | C7: Karthik Subramanian | D7: Oct 2026 (Monthly) | E7: 900 | F7: 0 | G7: =E7+F7 | H7: 900 | I7: 0 | J7: 0 | K7: =G7-(H7+I7+J7) | L7: Paid in Full | M7: Wallet balance debit | N7: 2026-10-01
A8: INV-2026-1006 | B8: TN-SUB-107 | C8: Manoj Prabhakar | D8: Oct 2026 (Monthly) | E8: 2850 | F8: 450 | G8: =E8+F8 | H8: 2850 | I8: 450 | J8: 0 | K8: =G8-(H8+I8+J8) | L8: Paid in Full | M8: Wallet (2850) + UPI (450) | N8: 2026-10-01

Sheet 📦 Inventory & Demand Forecast
A1: TOMORROWNEEDS - DAILY RECURRING DEMAND & PROCUREMENT PLANNER
A2: Item ID | B2: Item Name | C2: Category | D2: Pack Size / Unit | E2: Active Daily Subscriptions Demand | F2: Buffer / Extra On-Demand Orders | G2: Total Daily Procurement Target | H2: Vendor Cost / Unit (₹) | I2: Total Daily Procurement Budget (₹) | J2: Retail Selling Price (₹) | K2: Daily Margin (₹)
A3: ITM-01 | B3: Fresh Buffalo Milk | C3: Milk & Dairy | D3: 1 Litre Pouch | E3: 18 | F3: 5 | G3: =E3+F3 | H3: 52 | I3: =G3*H3 | J3: 70 | K3: =(J3-H3)*G3
A4: ITM-02 | B4: Country Cow Milk (Pure A2) | C4: Milk & Dairy | D4: 500 ml Pouch | E4: 24 | F4: 6 | G4: =E4+F4 | H4: 30 | I4: =G4*H4 | J4: 40 | K4: =(J4-H4)*G4
A5: ITM-03 | B5: Fresh Idli/Dosa Batter | C5: Batters | D5: 1 Kg Pouch | E5: 14 | F5: 8 | G5: =E5+F5 | H5: 35 | I5: =G5*H5 | J5: 50 | K5: =(J5-H5)*G5
A6: ITM-04 | B6: Organic Vegetable Basket | C6: Vegetables | D6: 5 Kg Assorted | E6: 8 | F6: 3 | G6: =E6+F6 | H6: 240 | I6: =G6*H6 | J6: 350 | K6: =(J6-H6)*G6
A7: ITM-05 | B7: Fresh Spinach & Greens Combo | C7: Greens | D7: 2 Bunches | E7: 12 | F7: 4 | G7: =E7+F7 | H7: 18 | I7: =G7*H7 | J7: 30 | K7: =(J7-H7)*G7
A8: ITM-06 | B8: Cold-Pressed Sesame Oil | C8: Oils | D8: 1 Litre Bottle | E8: 5 | F8: 2 | G8: =E8+F8 | H8: 280 | I8: =G8*H8 | J8: 380 | K8: =(J8-H8)*G8
